tom_nonsidereal_airmass/__init__.py
tom_nonsidereal_airmass/admin.py
tom_nonsidereal_airmass/apps.py
tom_nonsidereal_airmass/forms.py
tom_nonsidereal_airmass/models.py
tom_nonsidereal_airmass/tests.py
tom_nonsidereal_airmass/utils.py
tom_nonsidereal_airmass/views.py
tom_nonsidereal_airmass/migrations/__init__.py
tom_nonsidereal_airmass/templatetags/__init__.py
tom_nonsidereal_airmass/templatetags/nonsidereal_airmass_extras.py
tom_nonsidereal_airmass-0.1.0.dist-info/LICENSE
tom_nonsidereal_airmass-0.1.0.dist-info/METADATA
tom_nonsidereal_airmass-0.1.0.dist-info/WHEEL
tom_nonsidereal_airmass-0.1.0.dist-info/top_level.txt
tom_nonsidereal_airmass-0.1.0.dist-info/RECORD
